drb/drivers/image/__init__.py
drb/drivers/image/_version.py
drb/drivers/image/base_node.py
drb/drivers/image/list_node.py
drb/drivers/image/simple_node.py
drb/exceptions/image.py
drb/topics/image/__init__.py
drb/topics/image/cortex.yml
drb_driver_image-1.3.0.dist-info/LICENCE.txt
drb_driver_image-1.3.0.dist-info/METADATA
drb_driver_image-1.3.0.dist-info/WHEEL
drb_driver_image-1.3.0.dist-info/entry_points.txt
drb_driver_image-1.3.0.dist-info/top_level.txt
drb_driver_image-1.3.0.dist-info/RECORD
