Metadata-Version: 2.1
Name: drb-driver-image
Version: 1.3.0
Summary: DRB Image driver
Author: GAEL Systems
Author-email: drb-python@gael.fr
License: LGPLv3
Project-URL: Documentation, http://drb-python.gitlab.io/impl/image
Project-URL: Source, https://gitlab.com/drb-python/impl/image
Classifier: Programming Language :: Python :: 3.8
Classifier: Environment :: Plugins
Classifier: License :: OSI Approved :: GNU Lesser General Public License v3 (LGPLv3)
Requires-Python: >=3.8
License-File: LICENCE.txt
Requires-Dist: drb ~=2.2.0
Requires-Dist: numpy ==1.24.1
Requires-Dist: rasterio >=1.3.5
Requires-Dist: xarray ==2023.1.0
